<annotation>
	<folder>tatu7</folder>
	<filename>41166.jpg</filename>
	<path>//Aisovdsrv/ttestershare/=TTTAAAA=/tatu7/41166.jpg</path>
	<source>
		<database>Unknown</database>
	</source>
	<size>
		<width>574</width>
		<height>1024</height>
		<depth>3</depth>
	</size>
	<segmented>0</segmented>
	<object>
		<name>tatu7_zmeya</name>
		<pose>Unspecified</pose>
		<truncated>0</truncated>
		<difficult>0</difficult>
		<bndbox>
			<xmin>172</xmin>
			<ymin>123</ymin>
			<xmax>428</xmax>
			<ymax>1002</ymax>
		</bndbox>
	</object>
</annotation>
