<annotation>
	<folder>tatu5</folder>
	<filename>114453.jpg</filename>
	<path>//Aisovdsrv/ttestershare/=TTTAAAA=/tatu5/114453.jpg</path>
	<source>
		<database>Unknown</database>
	</source>
	<size>
		<width>683</width>
		<height>1024</height>
		<depth>3</depth>
	</size>
	<segmented>0</segmented>
	<object>
		<name>tatu8_kot</name>
		<pose>Unspecified</pose>
		<truncated>0</truncated>
		<difficult>0</difficult>
		<bndbox>
			<xmin>170</xmin>
			<ymin>129</ymin>
			<xmax>561</xmax>
			<ymax>749</ymax>
		</bndbox>
	</object>
</annotation>
