<annotation>
	<folder>tatu9</folder>
	<filename>103692.jpg</filename>
	<path>//aisovdsrv/ttestershare/=TTTAAAA=/tatu9/103692.jpg</path>
	<source>
		<database>Unknown</database>
	</source>
	<size>
		<width>768</width>
		<height>1024</height>
		<depth>3</depth>
	</size>
	<segmented>0</segmented>
	<object>
		<name>tatu9_krest</name>
		<pose>Unspecified</pose>
		<truncated>0</truncated>
		<difficult>0</difficult>
		<bndbox>
			<xmin>340</xmin>
			<ymin>297</ymin>
			<xmax>516</xmax>
			<ymax>601</ymax>
		</bndbox>
	</object>
	<object>
		<name>tatu3_bukva</name>
		<pose>Unspecified</pose>
		<truncated>0</truncated>
		<difficult>0</difficult>
		<bndbox>
			<xmin>419</xmin>
			<ymin>268</ymin>
			<xmax>454</xmax>
			<ymax>301</ymax>
		</bndbox>
	</object>
</annotation>
