<annotation>
	<folder>tatu9</folder>
	<filename>32227.jpg</filename>
	<path>//Aisovdsrv/ttestershare/=TTTAAAA=/tatu9/32227.jpg</path>
	<source>
		<database>Unknown</database>
	</source>
	<size>
		<width>1280</width>
		<height>960</height>
		<depth>3</depth>
	</size>
	<segmented>0</segmented>
	<object>
		<name>tatu9_krest</name>
		<pose>Unspecified</pose>
		<truncated>0</truncated>
		<difficult>0</difficult>
		<bndbox>
			<xmin>495</xmin>
			<ymin>187</ymin>
			<xmax>863</xmax>
			<ymax>857</ymax>
		</bndbox>
	</object>
</annotation>
